AUTHORS.rst
CONTRIBUTING.rst
HISTORY.rst
LICENSE
MANIFEST.in
README.rst
setup.cfg
setup.py
aiohttp_swaggerify/__init__.py
aiohttp_swaggerify.egg-info/PKG-INFO
aiohttp_swaggerify.egg-info/SOURCES.txt
aiohttp_swaggerify.egg-info/dependency_links.txt
aiohttp_swaggerify.egg-info/not-zip-safe
aiohttp_swaggerify.egg-info/top_level.txt
docs/Makefile
docs/authors.rst
docs/conf.py
docs/contributing.rst
docs/history.rst
docs/index.rst
docs/installation.rst
docs/make.bat
docs/readme.rst
docs/usage.rst
tests/__init__.py
tests/test_aiohttp_swaggerify.py
tests/validate_swagger.json