Metadata-Version: 1.1
Name: aiohttp-swaggerify
Version: 0.1.0
Summary: Library to automatically generate swagger2.0 definition for aiohttp endpoints
Home-page: https://github.com/dchaplinsky/aiohttp_swaggerify
Author: Dmitry Chaplinsky
Author-email: chaplinsky.dmitry@gmail.com
License: MIT license
Keywords: aiohttp_swaggerify
Platform: UNKNOWN
Classifier: Development Status :: 2 - Pre-Alpha
Classifier: Intended Audience :: Developers
Classifier: License :: OSI Approved :: MIT License
Classifier: Natural Language :: English
Classifier: Programming Language :: Python :: 3
Classifier: Programming Language :: Python :: 3.5
